{
  "target_fiscal_year": 2027,
  "status": "skipped",
  "status_reason": "no_form_url",
  "status_detail": null,
  "member": {
    "full_name": "Adelita Grijalva",
    "first_name": "Adelita",
    "last_name": "Grijalva",
    "chamber": "House",
    "party": "Democrat",
    "state_code": "AZ",
    "district": "7",
    "form_url": null,
    "deadline": null,
    "comment": null,
    "submitted": false,
    "past_caucus_signatory": false,
    "caucus_member": false,
    "appropriator": false,
    "authorizer": false,
    "nasa_center": false,
    "bioguide_id": "G000606",
    "official_url": "https://grijalva.house.gov/",
    "contact_form_url": null,
    "phone": "202-225-2435",
    "office_address": "1203 Longworth House Office Building Washington DC 20515-0307",
    "district_offices": null,
    "state_district": "AZ-07",
    "district_padded": "07",
    "member_key": "AZ-07_grijalva"
  },
  "form_analysis": null,
  "nasa_context": {
    "state_code": "AZ",
    "state_name": "Arizona",
    "district": "07",
    "spending_by_year": {
      "2023": 70640507.08,
      "2024": 45744138.39,
      "2025": 81021864.28
    },
    "annual_total_spending_by_year": {
      "2023": 70640507.08,
      "2024": 45744138.39,
      "2025": 81021864.28
    },
    "top_contracts": [
      {
        "award_id": "GSFC0200208DNAS502105",
        "generated_unique_award_id": "CONT_AWD_GSFC0200208DNAS502105_8000_-NONE-_-NONE-",
        "recipient_name": "University of Arizona",
        "recipient_id": "4f121097-1173-861e-ba01-a877858acd3d-C",
        "award_amount": 486654377.0,
        "description": "Next generation Space Telescope nircam the contractor shall provide the personnel, services, materials, equipment, and facilities needed to manage and perform phases a through E of the selected near-infrared camera (NIRCAM) instrument flight investigation.  The contractor is responsible for ensuring that all the requirements in the contract are met.  The contractor shall perform the following activities within each phase: phase a:  the contractor shall define the nircam science investigation, science payload, and Mission Operations and Data systems. The contractor shall document its findings and conclusions in a concept study report that it shall prepare and deliver to the government.  The contractor shall define and refine its Education and Public Outreach plan during phase a. Phases b-d:  the contractor shall design, analyze, develop, fabricate, calibrate, integrate, test and deliver the nircam science instrument to National Aeronautics and Space Administration (NASA) goddard Space flight center'S (GSFC) James Webb Space Telescope (JWST) project. The contractor shall also plan and prepare for the Mission Operations phase during phases b-d. This shall include developing an Operations and calibration strategy, defining and planning the Guaranteed Time Observations (GTO) science program, preparing and testing ground software in collaboration with the science and Operations center, and participating in Mission simulations.  The contractor shall execute its Education and Public Outreach (E/PO) plan during phases b-d. Phases E:  the contractor shall provide the necessary personnel, services, materials, equipment, and facilities needed to perform Mission Operations and Data Analysis (MO&DA) activities.  The contractor shall direct the execution of its gto science program during phase E.  The contractor shall continue to execute its E/po plan during phase E.",
        "start_date": "2002-07-17",
        "end_date": "2027-09-30",
        "category": "contract",
        "place_of_performance": {
          "location_country_code": "USA",
          "country_name": "UNITED STATES",
          "state_code": "AZ",
          "state_name": "Arizona",
          "city_name": "TUCSON",
          "county_code": "019",
          "county_name": "PIMA",
          "congressional_code": "07",
          "zip4": "857210158",
          "zip5": "85721"
        },
        "recipient_location": {
          "location_country_code": "USA",
          "country_name": "UNITED STATES",
          "state_code": "AZ",
          "state_name": "Arizona",
          "city_name": "TUCSON",
          "county_code": "019",
          "county_name": "PIMA",
          "address_line1": "888 N EUCLID AVE, ROOM 510",
          "address_line2": null,
          "address_line3": null,
          "congressional_code": "07",
          "zip4": "0158",
          "zip5": "85721",
          "foreign_postal_code": null,
          "foreign_province": null
        },
        "generated_award_summary": "Developing and operating the JWST's primary near-infrared science instrument."
      },
      {
        "award_id": "NNM10AA11C",
        "generated_unique_award_id": "CONT_AWD_NNM10AA11C_8000_-NONE-_-NONE-",
        "recipient_name": "University of Arizona",
        "recipient_id": "4f121097-1173-861e-ba01-a877858acd3d-C",
        "award_amount": 132320209.58,
        "description": "Osiris - rex asteroid sample return mission. 1.1 osiris - rex deputy principal investigator, heather enos, osiris - rex business manager, Dr. Drake and Dr. Lauretta will have the overall responsibility for the development and delivery of the osiris - rex phase a Concept Study Report. The Concept Study Report must meet the requirements delineated in part ii of the statement of work. 1.2 the Concept Study Report (CSR) will include, but not limited to, proposed level 1 science requirements, criteria for full mission success satisfying the baseline science mission and criteria for minimum mission success satisfying the threshold science mission. 1.3 the ua management team will work closely with the GSFC and lm management teams to refine the proposed osiris - rex mission costs. The ua management team will work closely with GSFC project management and lm to assess the robustness and feasibility of the cost and schedules. The ua management team will have the lead for the cost section of the Report. 1.4 the ua management team will provide support in the development of required international agreements such as technical assistance agreements and itar licenses. 1.5 the ua management team will oversee the phase a contract with instrument lead, Dr. Phil christensen, asu. 1.6 the ua management team will provide inputs and validation support to the GSFC integrated master scheduler. 1.7 deputy PI, Dr. Lauretta, will lead the development of the E/po and student collaboration plans. 1.8 the University of Arizona (UA) will support the OSIRIS-REx site visit at lockheed martin, littleton, co.",
        "start_date": "2010-03-16",
        "end_date": "2027-03-31",
        "category": "contract",
        "place_of_performance": {
          "location_country_code": "USA",
          "country_name": "UNITED STATES",
          "state_code": "AZ",
          "state_name": "Arizona",
          "city_name": "TUCSON",
          "county_code": "019",
          "county_name": "PIMA",
          "congressional_code": "07",
          "zip4": "857194824",
          "zip5": "85719"
        },
        "recipient_location": {
          "location_country_code": "USA",
          "country_name": "UNITED STATES",
          "state_code": "AZ",
          "state_name": "Arizona",
          "city_name": "TUCSON",
          "county_code": "019",
          "county_name": "PIMA",
          "address_line1": "888 N EUCLID AVE",
          "address_line2": null,
          "address_line3": null,
          "congressional_code": "07",
          "zip4": "4824",
          "zip5": "85719",
          "foreign_postal_code": null,
          "foreign_province": null
        },
        "generated_award_summary": "Defining science requirements for OSIRIS-REx asteroid sample return."
      },
      {
        "award_id": "80AFRC24FA019",
        "generated_unique_award_id": "CONT_AWD_80AFRC24FA019_8000_80AFRC24DA006_8000",
        "recipient_name": "World View Enterprises Inc",
        "recipient_id": "6b22a066-205b-ad96-0b42-74b671fe2418-C",
        "award_amount": 385197.0,
        "description": "Flight and payload integration services gamma-ray and antimatter survey (GRAMS) payload under profile 2: exposure to high-altitude and long-duration flight.",
        "start_date": "2024-03-15",
        "end_date": "2026-06-01",
        "category": "contract",
        "place_of_performance": {
          "location_country_code": "USA",
          "country_name": "UNITED STATES",
          "state_code": "AZ",
          "state_name": "Arizona",
          "city_name": "TUCSON",
          "county_code": "019",
          "county_name": "PIMA",
          "congressional_code": "07",
          "zip4": "857569553",
          "zip5": "85756"
        },
        "recipient_location": {
          "location_country_code": "USA",
          "country_name": "UNITED STATES",
          "state_code": "AZ",
          "state_name": "Arizona",
          "city_name": "TUCSON",
          "county_code": "019",
          "county_name": "PIMA",
          "address_line1": "1805 E AEROSPACE PKWY",
          "address_line2": null,
          "address_line3": null,
          "congressional_code": "07",
          "zip4": "9553",
          "zip5": "85756",
          "foreign_postal_code": null,
          "foreign_province": null
        },
        "generated_award_summary": "Preparing the GRAMS antimatter survey instrument for long-duration flight testing."
      }
    ],
    "top_grants": [
      {
        "award_id": "80NSSC22M0081",
        "generated_unique_award_id": "ASST_NON_80NSSC22M0081_080",
        "recipient_name": "University of Arizona",
        "recipient_id": "4f121097-1173-861e-ba01-a877858acd3d-C",
        "award_amount": 18525273.24,
        "description": "All components of this design are trl 6 or higher and require no technology development  making this in line with the scope of the astrophysics pioneers call.",
        "start_date": "2022-04-01",
        "end_date": "2026-06-30",
        "category": "grant",
        "place_of_performance": {
          "location_country_code": "USA",
          "country_name": "UNITED STATES",
          "state_code": "AZ",
          "state_name": "Arizona",
          "city_name": "TUCSON",
          "county_code": "019",
          "county_name": "PIMA",
          "congressional_code": "07",
          "zip4": "85719-4824",
          "zip5": "85719"
        },
        "recipient_location": {
          "location_country_code": "USA",
          "country_name": "UNITED STATES",
          "state_code": "AZ",
          "state_name": "Arizona",
          "city_name": "TUCSON",
          "county_code": "019",
          "county_name": "PIMA",
          "address_line1": "888 N EUCLID AVE RM 510",
          "address_line2": null,
          "address_line3": null,
          "congressional_code": "07",
          "zip4": "4824",
          "zip5": "85719",
          "foreign_postal_code": null,
          "foreign_province": null
        },
        "generated_award_summary": "Maturing the design for a high-priority astrophysics mission."
      },
      {
        "award_id": "80NSSC21K0593",
        "generated_unique_award_id": "ASST_NON_80NSSC21K0593_080",
        "recipient_name": "University of Arizona",
        "recipient_id": "4f121097-1173-861e-ba01-a877858acd3d-C",
        "award_amount": 6160513.0,
        "description": "With the discovery that habitable planets may be very common  one of the most compelling and timely questions to answer is: which nearby planetary systems are likely to host habitable planets and life? Advancing our knowledge on this question will",
        "start_date": "2021-05-01",
        "end_date": "2026-04-30",
        "category": "grant",
        "place_of_performance": {
          "location_country_code": "USA",
          "country_name": "UNITED STATES",
          "state_code": "AZ",
          "state_name": "Arizona",
          "city_name": "TUCSON",
          "county_code": "019",
          "county_name": "PIMA",
          "congressional_code": "07",
          "zip4": "85719-4824",
          "zip5": "85719"
        },
        "recipient_location": {
          "location_country_code": "USA",
          "country_name": "UNITED STATES",
          "state_code": "AZ",
          "state_name": "Arizona",
          "city_name": "TUCSON",
          "county_code": "019",
          "county_name": "PIMA",
          "address_line1": "888 N EUCLID AVE RM 510",
          "address_line2": null,
          "address_line3": null,
          "congressional_code": "07",
          "zip4": "4824",
          "zip5": "85719",
          "foreign_postal_code": null,
          "foreign_province": null
        },
        "generated_award_summary": "Assessing life potential in nearby planetary systems."
      },
      {
        "award_id": "80NSSC24K1458",
        "generated_unique_award_id": "ASST_NON_80NSSC24K1458_080",
        "recipient_name": "University of Arizona",
        "recipient_id": "4f121097-1173-861e-ba01-a877858acd3d-C",
        "award_amount": 5899119.0,
        "description": "24-pimove24-0003  odin - optomechanical-distributed instrument for inertial sensing and navigation",
        "start_date": "2024-08-01",
        "end_date": "2027-07-31",
        "category": "grant",
        "place_of_performance": {
          "location_country_code": "USA",
          "country_name": "UNITED STATES",
          "state_code": "AZ",
          "state_name": "Arizona",
          "city_name": "TUCSON",
          "county_code": "019",
          "county_name": "PIMA",
          "congressional_code": "07",
          "zip4": "85721-0178",
          "zip5": "85721"
        },
        "recipient_location": {
          "location_country_code": "USA",
          "country_name": "UNITED STATES",
          "state_code": "AZ",
          "state_name": "Arizona",
          "city_name": "TUCSON",
          "county_code": "019",
          "county_name": "PIMA",
          "address_line1": "845 N PARK AVE RM 538",
          "address_line2": null,
          "address_line3": null,
          "congressional_code": "07",
          "zip4": "0000",
          "zip5": "85721",
          "foreign_postal_code": null,
          "foreign_province": null
        },
        "generated_award_summary": "Developing next-generation inertial navigation technology."
      },
      {
        "award_id": "80NSSC24K1187",
        "generated_unique_award_id": "ASST_NON_80NSSC24K1187_080",
        "recipient_name": "University of Arizona",
        "recipient_id": "4f121097-1173-861e-ba01-a877858acd3d-C",
        "award_amount": 4967643.0,
        "description": "23-yorpd23_2-0018  the catalina sky survey for near-earth objects",
        "start_date": "2024-09-01",
        "end_date": "2027-08-31",
        "category": "grant",
        "place_of_performance": {
          "location_country_code": "USA",
          "country_name": "UNITED STATES",
          "state_code": "AZ",
          "state_name": "Arizona",
          "city_name": "TUCSON",
          "county_code": "019",
          "county_name": "PIMA",
          "congressional_code": "07",
          "zip4": "85721-0158",
          "zip5": "85721"
        },
        "recipient_location": {
          "location_country_code": "USA",
          "country_name": "UNITED STATES",
          "state_code": "AZ",
          "state_name": "Arizona",
          "city_name": "TUCSON",
          "county_code": "019",
          "county_name": "PIMA",
          "address_line1": "845 N PARK AVE RM 538",
          "address_line2": null,
          "address_line3": null,
          "congressional_code": "07",
          "zip4": "0000",
          "zip5": "85721",
          "foreign_postal_code": null,
          "foreign_province": null
        },
        "generated_award_summary": "Tracking near-Earth objects via the Catalina Sky Survey."
      },
      {
        "award_id": "80NSSC22M0026",
        "generated_unique_award_id": "ASST_NON_80NSSC22M0026_080",
        "recipient_name": "Planetary Science Institute",
        "recipient_id": "3214acd0-9912-82a2-50bc-144803c391a7-C",
        "award_amount": 4133074.23,
        "description": "Renewal for the cooperative agreement notice - the small bodies node of NASA'S planetary data system with the minor planet center",
        "start_date": "2021-12-01",
        "end_date": "2026-11-30",
        "category": "grant",
        "place_of_performance": {
          "location_country_code": "USA",
          "country_name": "UNITED STATES",
          "state_code": "AZ",
          "state_name": "Arizona",
          "city_name": "TUCSON",
          "county_code": "019",
          "county_name": "PIMA",
          "congressional_code": "07",
          "zip4": "85719-2395",
          "zip5": "85719"
        },
        "recipient_location": {
          "location_country_code": "USA",
          "country_name": "UNITED STATES",
          "state_code": "AZ",
          "state_name": "Arizona",
          "city_name": "TUCSON",
          "county_code": "019",
          "county_name": "PIMA",
          "address_line1": "1700 E FORT LOWELL RD STE 106",
          "address_line2": null,
          "address_line3": null,
          "congressional_code": "07",
          "zip4": "2395",
          "zip5": "85719",
          "foreign_postal_code": null,
          "foreign_province": null
        },
        "generated_award_summary": "Maintaining the central archive for asteroid and comet observations."
      },
      {
        "award_id": "80NSSC25K7306",
        "generated_unique_award_id": "ASST_NON_80NSSC25K7306_080",
        "recipient_name": "University of Arizona",
        "recipient_id": "4f121097-1173-861e-ba01-a877858acd3d-C",
        "award_amount": 3041172.0,
        "description": "Execute a balanced science program based on discipline-specific guidance from the national academies of sciences  engineering  and medicine  administration priorities  and direction from congress. Participate as a key partner and enabler in the agency S exploration initiative  focusing on scientific research of  on  and from the moon  lunar orbit  Mars  and beyond. Advance discovery in emerging fields by identifying and exploiting cross-disciplinary opportunities between traditional science disciplines. Develop a directorate-wide  target-user focused approach to applied programs  including Earth science applications  space weather  planetary defense  and space situational awareness.",
        "start_date": "2024-11-07",
        "end_date": "2028-01-13",
        "category": "grant",
        "place_of_performance": {
          "location_country_code": "USA",
          "country_name": "UNITED STATES",
          "state_code": "AZ",
          "state_name": "Arizona",
          "city_name": "TUCSON",
          "county_code": "019",
          "county_name": "PIMA",
          "congressional_code": "07",
          "zip4": "85721-0178",
          "zip5": "85721"
        },
        "recipient_location": {
          "location_country_code": "USA",
          "country_name": "UNITED STATES",
          "state_code": "AZ",
          "state_name": "Arizona",
          "city_name": "TUCSON",
          "county_code": "019",
          "county_name": "PIMA",
          "address_line1": "845 N PARK AVE RM 538",
          "address_line2": null,
          "address_line3": null,
          "congressional_code": "07",
          "zip4": "0000",
          "zip5": "85721",
          "foreign_postal_code": null,
          "foreign_province": null
        },
        "generated_award_summary": "Enabling strategic scientific research supporting lunar and Martian exploration."
      },
      {
        "award_id": "80NSSC23K0327",
        "generated_unique_award_id": "ASST_NON_80NSSC23K0327_080",
        "recipient_name": "University of Arizona",
        "recipient_id": "4f121097-1173-861e-ba01-a877858acd3d-C",
        "award_amount": 2919855.0,
        "description": "22-psef22_2-0007 the kuiper materials imaging and characterization facility at the university of arizona",
        "start_date": "2022-12-07",
        "end_date": "2026-12-06",
        "category": "grant",
        "place_of_performance": {
          "location_country_code": "USA",
          "country_name": "UNITED STATES",
          "state_code": "AZ",
          "state_name": "Arizona",
          "city_name": "TUCSON",
          "county_code": "019",
          "county_name": "PIMA",
          "congressional_code": "07",
          "zip4": "85719-4824",
          "zip5": "85719"
        },
        "recipient_location": {
          "location_country_code": "USA",
          "country_name": "UNITED STATES",
          "state_code": "AZ",
          "state_name": "Arizona",
          "city_name": "TUCSON",
          "county_code": "019",
          "county_name": "PIMA",
          "address_line1": "888 N EUCLID AVE RM 510",
          "address_line2": null,
          "address_line3": null,
          "congressional_code": "07",
          "zip4": "4824",
          "zip5": "85719",
          "foreign_postal_code": null,
          "foreign_province": null
        },
        "generated_award_summary": "Operating advanced imaging for planetary material characterization."
      }
    ],
    "top_contract_recipients": [
      {
        "name": "University of Arizona",
        "recipient_id": "4f121097-1173-861e-ba01-a877858acd3d-C",
        "total_amount": 693339816.3500001,
        "award_count": 4,
        "award_type": "contract",
        "location": {
          "location_country_code": "USA",
          "country_name": "UNITED STATES",
          "state_code": "AZ",
          "state_name": "Arizona",
          "city_name": "TUCSON",
          "county_code": "019",
          "county_name": "PIMA",
          "address_line1": "888 N EUCLID AVE, ROOM 510",
          "address_line2": null,
          "address_line3": null,
          "congressional_code": "07",
          "zip4": "0158",
          "zip5": "85721",
          "foreign_postal_code": null,
          "foreign_province": null
        },
        "place_of_performance": {
          "location_country_code": "USA",
          "country_name": "UNITED STATES",
          "state_code": "AZ",
          "state_name": "Arizona",
          "city_name": "TUCSON",
          "county_code": "019",
          "county_name": "PIMA",
          "congressional_code": "07",
          "zip4": "857210158",
          "zip5": "85721"
        }
      },
      {
        "name": "Planetary Science Institute",
        "recipient_id": "3214acd0-9912-82a2-50bc-144803c391a7-C",
        "total_amount": 3226580.0,
        "award_count": 1,
        "award_type": "contract",
        "location": {
          "location_country_code": "USA",
          "country_name": "UNITED STATES",
          "state_code": "AZ",
          "state_name": "Arizona",
          "city_name": "TUCSON",
          "county_code": "019",
          "county_name": "PIMA",
          "address_line1": "1700 E FORT LOWELL RD STE 106",
          "address_line2": null,
          "address_line3": null,
          "congressional_code": "07",
          "zip4": "2395",
          "zip5": "85719",
          "foreign_postal_code": null,
          "foreign_province": null
        },
        "place_of_performance": {
          "location_country_code": "USA",
          "country_name": "UNITED STATES",
          "state_code": "AZ",
          "state_name": "Arizona",
          "city_name": "TUCSON",
          "county_code": "019",
          "county_name": "PIMA",
          "congressional_code": "07",
          "zip4": "857192395",
          "zip5": "85719"
        }
      },
      {
        "name": "World View Enterprises Inc",
        "recipient_id": "6b22a066-205b-ad96-0b42-74b671fe2418-C",
        "total_amount": 385197.0,
        "award_count": 1,
        "award_type": "contract",
        "location": {
          "location_country_code": "USA",
          "country_name": "UNITED STATES",
          "state_code": "AZ",
          "state_name": "Arizona",
          "city_name": "TUCSON",
          "county_code": "019",
          "county_name": "PIMA",
          "address_line1": "1805 E AEROSPACE PKWY",
          "address_line2": null,
          "address_line3": null,
          "congressional_code": "07",
          "zip4": "9553",
          "zip5": "85756",
          "foreign_postal_code": null,
          "foreign_province": null
        },
        "place_of_performance": {
          "location_country_code": "USA",
          "country_name": "UNITED STATES",
          "state_code": "AZ",
          "state_name": "Arizona",
          "city_name": "TUCSON",
          "county_code": "019",
          "county_name": "PIMA",
          "congressional_code": "07",
          "zip4": "857569553",
          "zip5": "85756"
        }
      },
      {
        "name": "4 D Technology Corporation",
        "recipient_id": "c647526e-3e88-a5af-2ce0-43d64e3a0256-C",
        "total_amount": 305470.25,
        "award_count": 3,
        "award_type": "contract",
        "location": {
          "location_country_code": "USA",
          "country_name": "UNITED STATES",
          "state_code": "AZ",
          "state_name": "Arizona",
          "city_name": "TUCSON",
          "county_code": "019",
          "county_name": "PIMA",
          "address_line1": "3280 E HEMISPHERE LOOP STE 146",
          "address_line2": null,
          "address_line3": null,
          "congressional_code": "07",
          "zip4": "5039",
          "zip5": "85706",
          "foreign_postal_code": null,
          "foreign_province": null
        },
        "place_of_performance": {
          "location_country_code": "USA",
          "country_name": "UNITED STATES",
          "state_code": "AZ",
          "state_name": "Arizona",
          "city_name": "TUCSON",
          "county_code": "019",
          "county_name": "PIMA",
          "congressional_code": "07",
          "zip4": "857065039",
          "zip5": "85706"
        }
      },
      {
        "name": "Dataforth Corporation",
        "recipient_id": "58b66c48-5a25-5e55-62ba-230b023b36b7-C",
        "total_amount": 52334.0,
        "award_count": 1,
        "award_type": "contract",
        "location": {
          "location_country_code": "USA",
          "country_name": "UNITED STATES",
          "state_code": "AZ",
          "state_name": "Arizona",
          "city_name": "TUCSON",
          "county_code": "019",
          "county_name": "PIMA",
          "address_line1": "3331 E HEMISPHERE LOOP",
          "address_line2": null,
          "address_line3": null,
          "congressional_code": "07",
          "zip4": "5011",
          "zip5": "85706",
          "foreign_postal_code": null,
          "foreign_province": null
        },
        "place_of_performance": {
          "location_country_code": "USA",
          "country_name": "UNITED STATES",
          "state_code": "AZ",
          "state_name": "Arizona",
          "city_name": "TUCSON",
          "county_code": "019",
          "county_name": "PIMA",
          "congressional_code": "07",
          "zip4": "857065011",
          "zip5": "85706"
        }
      },
      {
        "name": "Advalue Photonics Inc",
        "recipient_id": "a01c3742-a32c-5a7a-67a2-242bc15f9de7-C",
        "total_amount": 22227.4,
        "award_count": 1,
        "award_type": "contract",
        "location": {
          "location_country_code": "USA",
          "country_name": "UNITED STATES",
          "state_code": "AZ",
          "state_name": "Arizona",
          "city_name": "TUCSON",
          "county_code": "019",
          "county_name": "PIMA",
          "address_line1": "2700 E BILBY RD",
          "address_line2": null,
          "address_line3": null,
          "congressional_code": "07",
          "zip4": "4554",
          "zip5": "85706",
          "foreign_postal_code": null,
          "foreign_province": null
        },
        "place_of_performance": {
          "location_country_code": "USA",
          "country_name": "UNITED STATES",
          "state_code": "AZ",
          "state_name": "Arizona",
          "city_name": "TUCSON",
          "county_code": "019",
          "county_name": "PIMA",
          "congressional_code": "07",
          "zip4": "857064554",
          "zip5": "85706"
        }
      },
      {
        "name": "Paragon Space Development Corporation",
        "recipient_id": "85175c1c-93eb-a4a6-5eda-511e6458a5d7-C",
        "total_amount": 17974.96,
        "award_count": 1,
        "award_type": "contract",
        "location": {
          "location_country_code": "USA",
          "country_name": "UNITED STATES",
          "state_code": "AZ",
          "state_name": "Arizona",
          "city_name": "TUCSON",
          "county_code": "019",
          "county_name": "PIMA",
          "address_line1": "3481 E MICHIGAN ST",
          "address_line2": null,
          "address_line3": null,
          "congressional_code": "07",
          "zip4": "2221",
          "zip5": "85714",
          "foreign_postal_code": null,
          "foreign_province": null
        },
        "place_of_performance": {
          "location_country_code": "USA",
          "country_name": "UNITED STATES",
          "state_code": "AZ",
          "state_name": "Arizona",
          "city_name": "TUCSON",
          "county_code": "019",
          "county_name": "PIMA",
          "congressional_code": "07",
          "zip4": "857142221",
          "zip5": "85714"
        }
      }
    ],
    "top_grant_recipients": [
      {
        "name": "University of Arizona",
        "recipient_id": "4f121097-1173-861e-ba01-a877858acd3d-C",
        "total_amount": 60453980.370000005,
        "award_count": 10,
        "award_type": "grant",
        "location": {
          "location_country_code": "USA",
          "country_name": "UNITED STATES",
          "state_code": "AZ",
          "state_name": "Arizona",
          "city_name": "TUCSON",
          "county_code": "019",
          "county_name": "PIMA",
          "address_line1": "888 N EUCLID AVE RM 510",
          "address_line2": null,
          "address_line3": null,
          "congressional_code": "07",
          "zip4": "4824",
          "zip5": "85719",
          "foreign_postal_code": null,
          "foreign_province": null
        },
        "place_of_performance": {
          "location_country_code": "USA",
          "country_name": "UNITED STATES",
          "state_code": "AZ",
          "state_name": "Arizona",
          "city_name": "TUCSON",
          "county_code": "019",
          "county_name": "PIMA",
          "congressional_code": "07",
          "zip4": "85719-4824",
          "zip5": "85719"
        }
      },
      {
        "name": "Planetary Science Institute",
        "recipient_id": "3214acd0-9912-82a2-50bc-144803c391a7-C",
        "total_amount": 9618415.23,
        "award_count": 2,
        "award_type": "grant",
        "location": {
          "location_country_code": "USA",
          "country_name": "UNITED STATES",
          "state_code": "AZ",
          "state_name": "Arizona",
          "city_name": "TUCSON",
          "county_code": "019",
          "county_name": "PIMA",
          "address_line1": "1700 E FORT LOWELL RD STE 106",
          "address_line2": null,
          "address_line3": null,
          "congressional_code": "07",
          "zip4": "2395",
          "zip5": "85719",
          "foreign_postal_code": null,
          "foreign_province": null
        },
        "place_of_performance": {
          "location_country_code": "USA",
          "country_name": "UNITED STATES",
          "state_code": "AZ",
          "state_name": "Arizona",
          "city_name": "TUCSON",
          "county_code": "019",
          "county_name": "PIMA",
          "congressional_code": "07",
          "zip4": "85719-2395",
          "zip5": "85719"
        }
      }
    ],
    "total_contract_count": 14,
    "total_grant_count": 379
  },
  "raw_award_data": {
    "spending": {
      "2023": 70640507.08,
      "2024": 45744138.39,
      "2025": 81021864.28
    },
    "Top Active Awards": [
      {
        "Award Type": "contract",
        "Award ID": "GSFC0200208DNAS502105",
        "Recipient Name": "University of Arizona",
        "recipient_id": "4f121097-1173-861e-ba01-a877858acd3d-C",
        "Recipient Location": {
          "location_country_code": "USA",
          "country_name": "UNITED STATES",
          "state_code": "AZ",
          "state_name": "Arizona",
          "city_name": "TUCSON",
          "county_code": "019",
          "county_name": "PIMA",
          "address_line1": "888 N EUCLID AVE, ROOM 510",
          "address_line2": null,
          "address_line3": null,
          "congressional_code": "07",
          "zip4": "0158",
          "zip5": "85721",
          "foreign_postal_code": null,
          "foreign_province": null
        },
        "Place of Performance": {
          "location_country_code": "USA",
          "country_name": "UNITED STATES",
          "state_code": "AZ",
          "state_name": "Arizona",
          "city_name": "TUCSON",
          "county_code": "019",
          "county_name": "PIMA",
          "congressional_code": "07",
          "zip4": "857210158",
          "zip5": "85721"
        },
        "Award Amount": 486654377.0,
        "Start Date": "2002-07-17",
        "End Date": "2027-09-30",
        "Last Modified Date": "2025-09-15",
        "Base Obligation Date": "2002-07-17",
        "Description": "Next generation Space Telescope nircam the contractor shall provide the personnel, services, materials, equipment, and facilities needed to manage and perform phases a through E of the selected near-infrared camera (NIRCAM) instrument flight investigation.  The contractor is responsible for ensuring that all the requirements in the contract are met.  The contractor shall perform the following activities within each phase: phase a:  the contractor shall define the nircam science investigation, science payload, and Mission Operations and Data systems. The contractor shall document its findings and conclusions in a concept study report that it shall prepare and deliver to the government.  The contractor shall define and refine its Education and Public Outreach plan during phase a. Phases b-d:  the contractor shall design, analyze, develop, fabricate, calibrate, integrate, test and deliver the nircam science instrument to National Aeronautics and Space Administration (NASA) goddard Space flight center'S (GSFC) James Webb Space Telescope (JWST) project. The contractor shall also plan and prepare for the Mission Operations phase during phases b-d. This shall include developing an Operations and calibration strategy, defining and planning the Guaranteed Time Observations (GTO) science program, preparing and testing ground software in collaboration with the science and Operations center, and participating in Mission simulations.  The contractor shall execute its Education and Public Outreach (E/PO) plan during phases b-d. Phases E:  the contractor shall provide the necessary personnel, services, materials, equipment, and facilities needed to perform Mission Operations and Data Analysis (MO&DA) activities.  The contractor shall direct the execution of its gto science program during phase E.  The contractor shall continue to execute its E/po plan during phase E.",
        "generated_unique_award_id": "CONT_AWD_GSFC0200208DNAS502105_8000_-NONE-_-NONE-",
        "generated_award_summary": "Developing and operating the JWST's primary near-infrared science instrument."
      },
      {
        "Award Type": "contract",
        "Award ID": "NNM10AA11C",
        "Recipient Name": "University of Arizona",
        "recipient_id": "4f121097-1173-861e-ba01-a877858acd3d-C",
        "Recipient Location": {
          "location_country_code": "USA",
          "country_name": "UNITED STATES",
          "state_code": "AZ",
          "state_name": "Arizona",
          "city_name": "TUCSON",
          "county_code": "019",
          "county_name": "PIMA",
          "address_line1": "888 N EUCLID AVE",
          "address_line2": null,
          "address_line3": null,
          "congressional_code": "07",
          "zip4": "4824",
          "zip5": "85719",
          "foreign_postal_code": null,
          "foreign_province": null
        },
        "Place of Performance": {
          "location_country_code": "USA",
          "country_name": "UNITED STATES",
          "state_code": "AZ",
          "state_name": "Arizona",
          "city_name": "TUCSON",
          "county_code": "019",
          "county_name": "PIMA",
          "congressional_code": "07",
          "zip4": "857194824",
          "zip5": "85719"
        },
        "Award Amount": 132320209.58,
        "Start Date": "2010-03-16",
        "End Date": "2027-03-31",
        "Last Modified Date": "2025-12-03",
        "Base Obligation Date": "2010-03-16",
        "Description": "Osiris - rex asteroid sample return mission. 1.1 osiris - rex deputy principal investigator, heather enos, osiris - rex business manager, Dr. Drake and Dr. Lauretta will have the overall responsibility for the development and delivery of the osiris - rex phase a Concept Study Report. The Concept Study Report must meet the requirements delineated in part ii of the statement of work. 1.2 the Concept Study Report (CSR) will include, but not limited to, proposed level 1 science requirements, criteria for full mission success satisfying the baseline science mission and criteria for minimum mission success satisfying the threshold science mission. 1.3 the ua management team will work closely with the GSFC and lm management teams to refine the proposed osiris - rex mission costs. The ua management team will work closely with GSFC project management and lm to assess the robustness and feasibility of the cost and schedules. The ua management team will have the lead for the cost section of the Report. 1.4 the ua management team will provide support in the development of required international agreements such as technical assistance agreements and itar licenses. 1.5 the ua management team will oversee the phase a contract with instrument lead, Dr. Phil christensen, asu. 1.6 the ua management team will provide inputs and validation support to the GSFC integrated master scheduler. 1.7 deputy PI, Dr. Lauretta, will lead the development of the E/po and student collaboration plans. 1.8 the University of Arizona (UA) will support the OSIRIS-REx site visit at lockheed martin, littleton, co.",
        "generated_unique_award_id": "CONT_AWD_NNM10AA11C_8000_-NONE-_-NONE-",
        "generated_award_summary": "Defining science requirements for OSIRIS-REx asteroid sample return."
      },
      {
        "Award Type": "grant",
        "Award ID": "80NSSC22M0081",
        "Recipient Name": "University of Arizona",
        "recipient_id": "4f121097-1173-861e-ba01-a877858acd3d-C",
        "Recipient Location": {
          "location_country_code": "USA",
          "country_name": "UNITED STATES",
          "state_code": "AZ",
          "state_name": "Arizona",
          "city_name": "TUCSON",
          "county_code": "019",
          "county_name": "PIMA",
          "address_line1": "888 N EUCLID AVE RM 510",
          "address_line2": null,
          "address_line3": null,
          "congressional_code": "07",
          "zip4": "4824",
          "zip5": "85719",
          "foreign_postal_code": null,
          "foreign_province": null
        },
        "Place of Performance": {
          "location_country_code": "USA",
          "country_name": "UNITED STATES",
          "state_code": "AZ",
          "state_name": "Arizona",
          "city_name": "TUCSON",
          "county_code": "019",
          "county_name": "PIMA",
          "congressional_code": "07",
          "zip4": "85719-4824",
          "zip5": "85719"
        },
        "Award Amount": 18525273.24,
        "Start Date": "2022-04-01",
        "End Date": "2026-06-30",
        "Last Modified Date": "2024-12-20",
        "Base Obligation Date": "2022-04-15",
        "Description": "All components of this design are trl 6 or higher and require no technology development  making this in line with the scope of the astrophysics pioneers call.",
        "generated_unique_award_id": "ASST_NON_80NSSC22M0081_080",
        "generated_award_summary": "Maturing the design for a high-priority astrophysics mission."
      },
      {
        "Award Type": "grant",
        "Award ID": "80NSSC21K0593",
        "Recipient Name": "University of Arizona",
        "recipient_id": "4f121097-1173-861e-ba01-a877858acd3d-C",
        "Recipient Location": {
          "location_country_code": "USA",
          "country_name": "UNITED STATES",
          "state_code": "AZ",
          "state_name": "Arizona",
          "city_name": "TUCSON",
          "county_code": "019",
          "county_name": "PIMA",
          "address_line1": "888 N EUCLID AVE RM 510",
          "address_line2": null,
          "address_line3": null,
          "congressional_code": "07",
          "zip4": "4824",
          "zip5": "85719",
          "foreign_postal_code": null,
          "foreign_province": null
        },
        "Place of Performance": {
          "location_country_code": "USA",
          "country_name": "UNITED STATES",
          "state_code": "AZ",
          "state_name": "Arizona",
          "city_name": "TUCSON",
          "county_code": "019",
          "county_name": "PIMA",
          "congressional_code": "07",
          "zip4": "85719-4824",
          "zip5": "85719"
        },
        "Award Amount": 6160513.0,
        "Start Date": "2021-05-01",
        "End Date": "2026-04-30",
        "Last Modified Date": "2025-09-05",
        "Base Obligation Date": "2021-03-24",
        "Description": "With the discovery that habitable planets may be very common  one of the most compelling and timely questions to answer is: which nearby planetary systems are likely to host habitable planets and life? Advancing our knowledge on this question will",
        "generated_unique_award_id": "ASST_NON_80NSSC21K0593_080",
        "generated_award_summary": "Assessing life potential in nearby planetary systems."
      },
      {
        "Award Type": "grant",
        "Award ID": "80NSSC24K1458",
        "Recipient Name": "University of Arizona",
        "recipient_id": "4f121097-1173-861e-ba01-a877858acd3d-C",
        "Recipient Location": {
          "location_country_code": "USA",
          "country_name": "UNITED STATES",
          "state_code": "AZ",
          "state_name": "Arizona",
          "city_name": "TUCSON",
          "county_code": "019",
          "county_name": "PIMA",
          "address_line1": "845 N PARK AVE RM 538",
          "address_line2": null,
          "address_line3": null,
          "congressional_code": "07",
          "zip4": "0000",
          "zip5": "85721",
          "foreign_postal_code": null,
          "foreign_province": null
        },
        "Place of Performance": {
          "location_country_code": "USA",
          "country_name": "UNITED STATES",
          "state_code": "AZ",
          "state_name": "Arizona",
          "city_name": "TUCSON",
          "county_code": "019",
          "county_name": "PIMA",
          "congressional_code": "07",
          "zip4": "85721-0178",
          "zip5": "85721"
        },
        "Award Amount": 5899119.0,
        "Start Date": "2024-08-01",
        "End Date": "2027-07-31",
        "Last Modified Date": "2025-07-22",
        "Base Obligation Date": "2024-08-26",
        "Description": "24-pimove24-0003  odin - optomechanical-distributed instrument for inertial sensing and navigation",
        "generated_unique_award_id": "ASST_NON_80NSSC24K1458_080",
        "generated_award_summary": "Developing next-generation inertial navigation technology."
      },
      {
        "Award Type": "grant",
        "Award ID": "80NSSC24K1187",
        "Recipient Name": "University of Arizona",
        "recipient_id": "4f121097-1173-861e-ba01-a877858acd3d-C",
        "Recipient Location": {
          "location_country_code": "USA",
          "country_name": "UNITED STATES",
          "state_code": "AZ",
          "state_name": "Arizona",
          "city_name": "TUCSON",
          "county_code": "019",
          "county_name": "PIMA",
          "address_line1": "845 N PARK AVE RM 538",
          "address_line2": null,
          "address_line3": null,
          "congressional_code": "07",
          "zip4": "0000",
          "zip5": "85721",
          "foreign_postal_code": null,
          "foreign_province": null
        },
        "Place of Performance": {
          "location_country_code": "USA",
          "country_name": "UNITED STATES",
          "state_code": "AZ",
          "state_name": "Arizona",
          "city_name": "TUCSON",
          "county_code": "019",
          "county_name": "PIMA",
          "congressional_code": "07",
          "zip4": "85721-0158",
          "zip5": "85721"
        },
        "Award Amount": 4967643.0,
        "Start Date": "2024-09-01",
        "End Date": "2027-08-31",
        "Last Modified Date": "2025-08-20",
        "Base Obligation Date": "2024-07-19",
        "Description": "23-yorpd23_2-0018  the catalina sky survey for near-earth objects",
        "generated_unique_award_id": "ASST_NON_80NSSC24K1187_080",
        "generated_award_summary": "Tracking near-Earth objects via the Catalina Sky Survey."
      },
      {
        "Award Type": "grant",
        "Award ID": "80NSSC22M0026",
        "Recipient Name": "Planetary Science Institute",
        "recipient_id": "3214acd0-9912-82a2-50bc-144803c391a7-C",
        "Recipient Location": {
          "location_country_code": "USA",
          "country_name": "UNITED STATES",
          "state_code": "AZ",
          "state_name": "Arizona",
          "city_name": "TUCSON",
          "county_code": "019",
          "county_name": "PIMA",
          "address_line1": "1700 E FORT LOWELL RD STE 106",
          "address_line2": null,
          "address_line3": null,
          "congressional_code": "07",
          "zip4": "2395",
          "zip5": "85719",
          "foreign_postal_code": null,
          "foreign_province": null
        },
        "Place of Performance": {
          "location_country_code": "USA",
          "country_name": "UNITED STATES",
          "state_code": "AZ",
          "state_name": "Arizona",
          "city_name": "TUCSON",
          "county_code": "019",
          "county_name": "PIMA",
          "congressional_code": "07",
          "zip4": "85719-2395",
          "zip5": "85719"
        },
        "Award Amount": 4133074.23,
        "Start Date": "2021-12-01",
        "End Date": "2026-11-30",
        "Last Modified Date": "2025-07-07",
        "Base Obligation Date": "2021-12-02",
        "Description": "Renewal for the cooperative agreement notice - the small bodies node of NASA'S planetary data system with the minor planet center",
        "generated_unique_award_id": "ASST_NON_80NSSC22M0026_080",
        "generated_award_summary": "Maintaining the central archive for asteroid and comet observations."
      },
      {
        "Award Type": "grant",
        "Award ID": "80NSSC25K7306",
        "Recipient Name": "University of Arizona",
        "recipient_id": "4f121097-1173-861e-ba01-a877858acd3d-C",
        "Recipient Location": {
          "location_country_code": "USA",
          "country_name": "UNITED STATES",
          "state_code": "AZ",
          "state_name": "Arizona",
          "city_name": "TUCSON",
          "county_code": "019",
          "county_name": "PIMA",
          "address_line1": "845 N PARK AVE RM 538",
          "address_line2": null,
          "address_line3": null,
          "congressional_code": "07",
          "zip4": "0000",
          "zip5": "85721",
          "foreign_postal_code": null,
          "foreign_province": null
        },
        "Place of Performance": {
          "location_country_code": "USA",
          "country_name": "UNITED STATES",
          "state_code": "AZ",
          "state_name": "Arizona",
          "city_name": "TUCSON",
          "county_code": "019",
          "county_name": "PIMA",
          "congressional_code": "07",
          "zip4": "85721-0178",
          "zip5": "85721"
        },
        "Award Amount": 3041172.0,
        "Start Date": "2024-11-07",
        "End Date": "2028-01-13",
        "Last Modified Date": "2025-07-07",
        "Base Obligation Date": "2025-01-13",
        "Description": "Execute a balanced science program based on discipline-specific guidance from the national academies of sciences  engineering  and medicine  administration priorities  and direction from congress. Participate as a key partner and enabler in the agency S exploration initiative  focusing on scientific research of  on  and from the moon  lunar orbit  Mars  and beyond. Advance discovery in emerging fields by identifying and exploiting cross-disciplinary opportunities between traditional science disciplines. Develop a directorate-wide  target-user focused approach to applied programs  including Earth science applications  space weather  planetary defense  and space situational awareness.",
        "generated_unique_award_id": "ASST_NON_80NSSC25K7306_080",
        "generated_award_summary": "Enabling strategic scientific research supporting lunar and Martian exploration."
      },
      {
        "Award Type": "grant",
        "Award ID": "80NSSC23K0327",
        "Recipient Name": "University of Arizona",
        "recipient_id": "4f121097-1173-861e-ba01-a877858acd3d-C",
        "Recipient Location": {
          "location_country_code": "USA",
          "country_name": "UNITED STATES",
          "state_code": "AZ",
          "state_name": "Arizona",
          "city_name": "TUCSON",
          "county_code": "019",
          "county_name": "PIMA",
          "address_line1": "888 N EUCLID AVE RM 510",
          "address_line2": null,
          "address_line3": null,
          "congressional_code": "07",
          "zip4": "4824",
          "zip5": "85719",
          "foreign_postal_code": null,
          "foreign_province": null
        },
        "Place of Performance": {
          "location_country_code": "USA",
          "country_name": "UNITED STATES",
          "state_code": "AZ",
          "state_name": "Arizona",
          "city_name": "TUCSON",
          "county_code": "019",
          "county_name": "PIMA",
          "congressional_code": "07",
          "zip4": "85719-4824",
          "zip5": "85719"
        },
        "Award Amount": 2919855.0,
        "Start Date": "2022-12-07",
        "End Date": "2026-12-06",
        "Last Modified Date": "2025-08-05",
        "Base Obligation Date": "2023-01-10",
        "Description": "22-psef22_2-0007 the kuiper materials imaging and characterization facility at the university of arizona",
        "generated_unique_award_id": "ASST_NON_80NSSC23K0327_080",
        "generated_award_summary": "Operating advanced imaging for planetary material characterization."
      },
      {
        "Award Type": "contract",
        "Award ID": "80AFRC24FA019",
        "Recipient Name": "World View Enterprises Inc",
        "recipient_id": "6b22a066-205b-ad96-0b42-74b671fe2418-C",
        "Recipient Location": {
          "location_country_code": "USA",
          "country_name": "UNITED STATES",
          "state_code": "AZ",
          "state_name": "Arizona",
          "city_name": "TUCSON",
          "county_code": "019",
          "county_name": "PIMA",
          "address_line1": "1805 E AEROSPACE PKWY",
          "address_line2": null,
          "address_line3": null,
          "congressional_code": "07",
          "zip4": "9553",
          "zip5": "85756",
          "foreign_postal_code": null,
          "foreign_province": null
        },
        "Place of Performance": {
          "location_country_code": "USA",
          "country_name": "UNITED STATES",
          "state_code": "AZ",
          "state_name": "Arizona",
          "city_name": "TUCSON",
          "county_code": "019",
          "county_name": "PIMA",
          "congressional_code": "07",
          "zip4": "857569553",
          "zip5": "85756"
        },
        "Award Amount": 385197.0,
        "Start Date": "2024-03-15",
        "End Date": "2026-06-01",
        "Last Modified Date": "2025-09-04",
        "Base Obligation Date": "2024-03-15",
        "Description": "Flight and payload integration services gamma-ray and antimatter survey (GRAMS) payload under profile 2: exposure to high-altitude and long-duration flight.",
        "generated_unique_award_id": "CONT_AWD_80AFRC24FA019_8000_80AFRC24DA006_8000",
        "generated_award_summary": "Preparing the GRAMS antimatter survey instrument for long-duration flight testing."
      }
    ],
    "Top Contract Recipients": [
      {
        "name": "University of Arizona",
        "recipient_id": "4f121097-1173-861e-ba01-a877858acd3d-C",
        "amount": 693339816.3500001,
        "award_count": 4,
        "location": {
          "location_country_code": "USA",
          "country_name": "UNITED STATES",
          "state_code": "AZ",
          "state_name": "Arizona",
          "city_name": "TUCSON",
          "county_code": "019",
          "county_name": "PIMA",
          "address_line1": "888 N EUCLID AVE, ROOM 510",
          "address_line2": null,
          "address_line3": null,
          "congressional_code": "07",
          "zip4": "0158",
          "zip5": "85721",
          "foreign_postal_code": null,
          "foreign_province": null
        },
        "place_of_performance": {
          "location_country_code": "USA",
          "country_name": "UNITED STATES",
          "state_code": "AZ",
          "state_name": "Arizona",
          "city_name": "TUCSON",
          "county_code": "019",
          "county_name": "PIMA",
          "congressional_code": "07",
          "zip4": "857210158",
          "zip5": "85721"
        },
        "type": "contract"
      },
      {
        "name": "Planetary Science Institute",
        "recipient_id": "3214acd0-9912-82a2-50bc-144803c391a7-C",
        "amount": 3226580.0,
        "award_count": 1,
        "location": {
          "location_country_code": "USA",
          "country_name": "UNITED STATES",
          "state_code": "AZ",
          "state_name": "Arizona",
          "city_name": "TUCSON",
          "county_code": "019",
          "county_name": "PIMA",
          "address_line1": "1700 E FORT LOWELL RD STE 106",
          "address_line2": null,
          "address_line3": null,
          "congressional_code": "07",
          "zip4": "2395",
          "zip5": "85719",
          "foreign_postal_code": null,
          "foreign_province": null
        },
        "place_of_performance": {
          "location_country_code": "USA",
          "country_name": "UNITED STATES",
          "state_code": "AZ",
          "state_name": "Arizona",
          "city_name": "TUCSON",
          "county_code": "019",
          "county_name": "PIMA",
          "congressional_code": "07",
          "zip4": "857192395",
          "zip5": "85719"
        },
        "type": "contract"
      },
      {
        "name": "World View Enterprises Inc",
        "recipient_id": "6b22a066-205b-ad96-0b42-74b671fe2418-C",
        "amount": 385197.0,
        "award_count": 1,
        "location": {
          "location_country_code": "USA",
          "country_name": "UNITED STATES",
          "state_code": "AZ",
          "state_name": "Arizona",
          "city_name": "TUCSON",
          "county_code": "019",
          "county_name": "PIMA",
          "address_line1": "1805 E AEROSPACE PKWY",
          "address_line2": null,
          "address_line3": null,
          "congressional_code": "07",
          "zip4": "9553",
          "zip5": "85756",
          "foreign_postal_code": null,
          "foreign_province": null
        },
        "place_of_performance": {
          "location_country_code": "USA",
          "country_name": "UNITED STATES",
          "state_code": "AZ",
          "state_name": "Arizona",
          "city_name": "TUCSON",
          "county_code": "019",
          "county_name": "PIMA",
          "congressional_code": "07",
          "zip4": "857569553",
          "zip5": "85756"
        },
        "type": "contract"
      },
      {
        "name": "4 D Technology Corporation",
        "recipient_id": "c647526e-3e88-a5af-2ce0-43d64e3a0256-C",
        "amount": 305470.25,
        "award_count": 3,
        "location": {
          "location_country_code": "USA",
          "country_name": "UNITED STATES",
          "state_code": "AZ",
          "state_name": "Arizona",
          "city_name": "TUCSON",
          "county_code": "019",
          "county_name": "PIMA",
          "address_line1": "3280 E HEMISPHERE LOOP STE 146",
          "address_line2": null,
          "address_line3": null,
          "congressional_code": "07",
          "zip4": "5039",
          "zip5": "85706",
          "foreign_postal_code": null,
          "foreign_province": null
        },
        "place_of_performance": {
          "location_country_code": "USA",
          "country_name": "UNITED STATES",
          "state_code": "AZ",
          "state_name": "Arizona",
          "city_name": "TUCSON",
          "county_code": "019",
          "county_name": "PIMA",
          "congressional_code": "07",
          "zip4": "857065039",
          "zip5": "85706"
        },
        "type": "contract"
      },
      {
        "name": "Dataforth Corporation",
        "recipient_id": "58b66c48-5a25-5e55-62ba-230b023b36b7-C",
        "amount": 52334.0,
        "award_count": 1,
        "location": {
          "location_country_code": "USA",
          "country_name": "UNITED STATES",
          "state_code": "AZ",
          "state_name": "Arizona",
          "city_name": "TUCSON",
          "county_code": "019",
          "county_name": "PIMA",
          "address_line1": "3331 E HEMISPHERE LOOP",
          "address_line2": null,
          "address_line3": null,
          "congressional_code": "07",
          "zip4": "5011",
          "zip5": "85706",
          "foreign_postal_code": null,
          "foreign_province": null
        },
        "place_of_performance": {
          "location_country_code": "USA",
          "country_name": "UNITED STATES",
          "state_code": "AZ",
          "state_name": "Arizona",
          "city_name": "TUCSON",
          "county_code": "019",
          "county_name": "PIMA",
          "congressional_code": "07",
          "zip4": "857065011",
          "zip5": "85706"
        },
        "type": "contract"
      },
      {
        "name": "Advalue Photonics Inc",
        "recipient_id": "a01c3742-a32c-5a7a-67a2-242bc15f9de7-C",
        "amount": 22227.4,
        "award_count": 1,
        "location": {
          "location_country_code": "USA",
          "country_name": "UNITED STATES",
          "state_code": "AZ",
          "state_name": "Arizona",
          "city_name": "TUCSON",
          "county_code": "019",
          "county_name": "PIMA",
          "address_line1": "2700 E BILBY RD",
          "address_line2": null,
          "address_line3": null,
          "congressional_code": "07",
          "zip4": "4554",
          "zip5": "85706",
          "foreign_postal_code": null,
          "foreign_province": null
        },
        "place_of_performance": {
          "location_country_code": "USA",
          "country_name": "UNITED STATES",
          "state_code": "AZ",
          "state_name": "Arizona",
          "city_name": "TUCSON",
          "county_code": "019",
          "county_name": "PIMA",
          "congressional_code": "07",
          "zip4": "857064554",
          "zip5": "85706"
        },
        "type": "contract"
      },
      {
        "name": "Paragon Space Development Corporation",
        "recipient_id": "85175c1c-93eb-a4a6-5eda-511e6458a5d7-C",
        "amount": 17974.96,
        "award_count": 1,
        "location": {
          "location_country_code": "USA",
          "country_name": "UNITED STATES",
          "state_code": "AZ",
          "state_name": "Arizona",
          "city_name": "TUCSON",
          "county_code": "019",
          "county_name": "PIMA",
          "address_line1": "3481 E MICHIGAN ST",
          "address_line2": null,
          "address_line3": null,
          "congressional_code": "07",
          "zip4": "2221",
          "zip5": "85714",
          "foreign_postal_code": null,
          "foreign_province": null
        },
        "place_of_performance": {
          "location_country_code": "USA",
          "country_name": "UNITED STATES",
          "state_code": "AZ",
          "state_name": "Arizona",
          "city_name": "TUCSON",
          "county_code": "019",
          "county_name": "PIMA",
          "congressional_code": "07",
          "zip4": "857142221",
          "zip5": "85714"
        },
        "type": "contract"
      }
    ],
    "Top Grant Recipients": [
      {
        "name": "University of Arizona",
        "recipient_id": "4f121097-1173-861e-ba01-a877858acd3d-C",
        "amount": 60453980.370000005,
        "award_count": 10,
        "location": {
          "location_country_code": "USA",
          "country_name": "UNITED STATES",
          "state_code": "AZ",
          "state_name": "Arizona",
          "city_name": "TUCSON",
          "county_code": "019",
          "county_name": "PIMA",
          "address_line1": "888 N EUCLID AVE RM 510",
          "address_line2": null,
          "address_line3": null,
          "congressional_code": "07",
          "zip4": "4824",
          "zip5": "85719",
          "foreign_postal_code": null,
          "foreign_province": null
        },
        "place_of_performance": {
          "location_country_code": "USA",
          "country_name": "UNITED STATES",
          "state_code": "AZ",
          "state_name": "Arizona",
          "city_name": "TUCSON",
          "county_code": "019",
          "county_name": "PIMA",
          "congressional_code": "07",
          "zip4": "85719-4824",
          "zip5": "85719"
        },
        "type": "grant"
      },
      {
        "name": "Planetary Science Institute",
        "recipient_id": "3214acd0-9912-82a2-50bc-144803c391a7-C",
        "amount": 9618415.23,
        "award_count": 2,
        "location": {
          "location_country_code": "USA",
          "country_name": "UNITED STATES",
          "state_code": "AZ",
          "state_name": "Arizona",
          "city_name": "TUCSON",
          "county_code": "019",
          "county_name": "PIMA",
          "address_line1": "1700 E FORT LOWELL RD STE 106",
          "address_line2": null,
          "address_line3": null,
          "congressional_code": "07",
          "zip4": "2395",
          "zip5": "85719",
          "foreign_postal_code": null,
          "foreign_province": null
        },
        "place_of_performance": {
          "location_country_code": "USA",
          "country_name": "UNITED STATES",
          "state_code": "AZ",
          "state_name": "Arizona",
          "city_name": "TUCSON",
          "county_code": "019",
          "county_name": "PIMA",
          "congressional_code": "07",
          "zip4": "85719-2395",
          "zip5": "85719"
        },
        "type": "grant"
      }
    ],
    "Total Contract Awards": 14,
    "Total Grant Awards": 379
  }
}